[
  {
    "pos_id": 44,
    "virtual_id": 1,
    "fid": 0,
    "won": 1,
    "pair": "XAUUSD",
    "dir": "Long",
    "signal_key": "sky_1",
    "ssngt": -0.853,
    "base": 10.0,
    "quote": 17799.100000000002,
    "time_o": "2021-10-31 23:31:52",
    "updates": 0,
    "open_price": 1779.91,
    "exit_high_price": 1783.06,
    "exit_low_price": 1778.33,
    "close_price": 1783.08,
    "pl_ratio_s": 1.99,
    "time_c": "2021-11-01 01:10:02",
    "profit": 31.69,
    "duration": "1:38:10",
    "touch_high_pip": 31.69999,
    "touch_low_pop": -8.2,
    "sprd": 0.0,
    "locked": 0.0
  },
  {
    "pos_id": 47,
    "virtual_id": 1,
    "fid": 0,
    "won": 1,
    "pair": "XAUUSD",
    "dir": "Long",
    "signal_key": "sky_1",
    "ssngt": -0.66,
    "base": 10.0,
    "quote": 17841.1,
    "time_o": "2021-11-01 11:14:37",
    "updates": 0,
    "open_price": 1784.11,
    "exit_high_price": 1788.07,
    "exit_low_price": 1782.12,
    "close_price": 1788.11,
    "pl_ratio_s": 1.98,
    "time_c": "2021-11-01 12:22:05",
    "profit": 40.0,
    "duration": "1:07:28",
    "touch_high_pip": 40.0,
    "touch_low_pop": -15.09999,
    "sprd": 0.0,
    "locked": 0.0
  },
  {
    "pos_id": 49,
    "virtual_id": 1,
    "fid": 0,
    "won": 1,
    "pair": "XAUUSD",
    "dir": "Long",
    "signal_key": "sky_1",
    "ssngt": -0.404,
    "base": 10.0,
    "quote": 17860.6,
    "time_o": "2021-11-01 13:34:13",
    "updates": 0,
    "open_price": 1786.06,
    "exit_high_price": 1790.45,
    "exit_low_price": 1783.86,
    "close_price": 1790.45,
    "pl_ratio_s": 1.99,
    "time_c": "2021-11-01 13:51:15",
    "profit": 43.9,
    "duration": "0:17:02",
    "touch_high_pip": 43.9,
    "touch_low_pop": -3.79999,
    "sprd": 0.0,
    "locked": 0.0
  },
  {
    "pos_id": 52,
    "virtual_id": 1,
    "fid": 0,
    "won": 1,
    "pair": "XAUUSD",
    "dir": "Long",
    "signal_key": "sky_1",
    "ssngt": -0.527,
    "base": 10.0,
    "quote": 17640.6,
    "time_o": "2021-11-03 18:32:15",
    "updates": 0,
    "open_price": 1764.06,
    "exit_high_price": 1771.14,
    "exit_low_price": 1760.51,
    "close_price": 1771.18,
    "pl_ratio_s": 1.99,
    "time_c": "2021-11-03 18:48:12",
    "profit": 71.2,
    "duration": "0:15:57",
    "touch_high_pip": 71.2,
    "touch_low_pop": -14.8,
    "sprd": 0.0,
    "locked": 0.0
  },
  {
    "pos_id": 53,
    "virtual_id": 1,
    "fid": 0,
    "won": 1,
    "pair": "XAUUSD",
    "dir": "Long",
    "signal_key": "sky_1",
    "ssngt": -0.018,
    "base": 10.0,
    "quote": 17694.9,
    "time_o": "2021-11-03 19:16:00",
    "updates": 0,
    "open_price": 1769.49,
    "exit_high_price": 1779.21,
    "exit_low_price": 1764.62,
    "close_price": 1779.42,
    "pl_ratio_s": 1.99,
    "time_c": "2021-11-04 10:49:01",
    "profit": 99.3,
    "duration": "15:33:01",
    "touch_high_pip": 99.3,
    "touch_low_pop": -9.4,
    "sprd": 0.0,
    "locked": 0.0
  },
  {
    "pos_id": 54,
    "virtual_id": 1,
    "fid": 0,
    "won": 1,
    "pair": "XAUUSD",
    "dir": "Long",
    "signal_key": "sky_1",
    "ssngt": 0.321,
    "base": 10.0,
    "quote": 17918.9,
    "time_o": "2021-11-04 13:29:23",
    "updates": 0,
    "open_price": 1791.89,
    "exit_high_price": 1799.87,
    "exit_low_price": 1787.89,
    "close_price": 1800.09,
    "pl_ratio_s": 1.99,
    "time_c": "2021-11-05 08:25:10",
    "profit": 81.99,
    "duration": "18:55:47",
    "touch_high_pip": 81.99999,
    "touch_low_pop": -18.0,
    "sprd": 0.0,
    "locked": 0.0
  },
  {
    "pos_id": 56,
    "virtual_id": 1,
    "fid": 0,
    "won": 1,
    "pair": "XAUUSD",
    "dir": "Long",
    "signal_key": "sky_1",
    "ssngt": 0.031,
    "base": 10.0,
    "quote": 17969.3,
    "time_o": "2021-11-05 13:50:54",
    "updates": 0,
    "open_price": 1796.93,
    "exit_high_price": 1807.29,
    "exit_low_price": 1791.74,
    "close_price": 1807.33,
    "pl_ratio_s": 1.99,
    "time_c": "2021-11-05 15:26:12",
    "profit": 103.99,
    "duration": "1:35:18",
    "touch_high_pip": 103.99999,
    "touch_low_pop": -10.8,
    "sprd": 0.0,
    "locked": 0.0
  },
  {
    "pos_id": 57,
    "virtual_id": 1,
    "fid": 0,
    "won": 1,
    "pair": "XAUUSD",
    "dir": "Long",
    "signal_key": "sky_1",
    "ssngt": 0.354,
    "base": 10.0,
    "quote": 18082.9,
    "time_o": "2021-11-05 16:08:50",
    "updates": 0,
    "open_price": 1808.29,
    "exit_high_price": 1816.79,
    "exit_low_price": 1804.03,
    "close_price": 1816.81,
    "pl_ratio_s": 1.99,
    "time_c": "2021-11-05 19:25:07",
    "profit": 85.19,
    "duration": "3:16:17",
    "touch_high_pip": 85.19999,
    "touch_low_pop": -5.0,
    "sprd": 0.0,
    "locked": 0.0
  }
]